[{"city":{"country":"US","coord":{"lon":-75.4557,"lat":43.2128},"sunrise":1611232021,"timezone":-18000,"sunset":1611266343,"name":"Rome","id":5134295,"population":33725},"cnt":40,"cod":"200","message":0,"list":[{"dt":1611241200,"pop":0.89,"visibility":3502,"dt_txt":"2021-01-21 15:00:00","snow":{"3h":1.65},"weather":[{"icon":"13d","description":"snow","main":"Snow","id":601}],"main":{"temp":268.76,"temp_min":268.76,"grnd_level":987,"temp_kf":-2.31,"humidity":91,"pressure":1005,"sea_level":1005,"feels_like":262.2,"temp_max":271.07},"clouds":{"all":95},"sys":{"pod":"d"},"wind":{"deg":223,"speed":5.55}},{"dt":1611252000,"pop":0.81,"visibility":10000,"dt_txt":"2021-01-21 18:00:00","snow":{"3h":0.49},"weather":[{"icon":"13d","description":"light snow","main":"Snow","id":600}],"main":{"temp":271.83,"temp_min":271.83,"grnd_level":984,"temp_kf":-1.46,"humidity":94,"pressure":1002,"sea_level":1002,"feels_like":265.5,"temp_max":273.29},"clouds":{"all":98},"sys":{"pod":"d"},"wind":{"deg":237,"speed":5.79}},{"dt":1611262800,"pop":0.57,"visibility":6048,"dt_txt":"2021-01-21 21:00:00","snow":{"3h":0.48},"weather":[{"icon":"13d","description":"light snow","main":"Snow","id":600}],"main":{"temp":272.98,"temp_min":272.98,"grnd_level":984,"temp_kf":-0.44,"humidity":95,"pressure":1000,"sea_level":1000,"feels_like":267.23,"temp_max":273.42},"clouds":{"all":99},"sys":{"pod":"d"},"wind":{"deg":231,"speed":5.2}},{"dt":1611273600,"pop":0.64,"visibility":1515,"dt_txt":"2021-01-22 00:00:00","snow":{"3h":1.85},"weather":[{"icon":"13n","description":"snow","main":"Snow","id":601}],"main":{"temp":273.23,"temp_min":273.23,"grnd_level":983,"temp_kf":-0.05,"humidity":97,"pressure":1000,"sea_level":1000,"feels_like":268.2,"temp_max":273.28},"clouds":{"all":100},"sys":{"pod":"n"},"wind":{"deg":257,"speed":4.28}},{"dt":1611284400,"pop":0.87,"visibility":515,"dt_txt":"2021-01-22 03:00:00","snow":{"3h":1.94},"weather":[{"icon":"13n","description":"snow","main":"Snow","id":601}],"main":{"temp":273.32,"temp_min":273.32,"grnd_level":983,"temp_kf":0,"humidity":97,"pressure":1000,"sea_level":1000,"feels_like":268.08,"temp_max":273.32},"clouds":{"all":99},"sys":{"pod":"n"},"wind":{"deg":241,"speed":4.6}},{"dt":1611295200,"pop":0.87,"visibility":316,"dt_txt":"2021-01-22 06:00:00","snow":{"3h":1.47},"weather":[{"icon":"13n","description":"light snow","main":"Snow","id":600}],"main":{"temp":272.5,"temp_min":272.5,"grnd_level":983,"temp_kf":0,"humidity":98,"pressure":1000,"sea_level":1000,"feels_like":266.46,"temp_max":272.5},"clouds":{"all":99},"sys":{"pod":"n"},"wind":{"deg":255,"speed":5.6}},{"dt":1611306000,"pop":0.68,"visibility":923,"dt_txt":"2021-01-22 09:00:00","snow":{"3h":1.13},"weather":[{"icon":"13n","description":"light snow","main":"Snow","id":600}],"main":{"temp":271.57,"temp_min":271.57,"grnd_level":984,"temp_kf":0,"humidity":97,"pressure":1001,"sea_level":1001,"feels_like":265.9,"temp_max":271.57},"clouds":{"all":97},"sys":{"pod":"n"},"wind":{"deg":253,"speed":4.87}},{"dt":1611316800,"pop":0.77,"visibility":631,"dt_txt":"2021-01-22 12:00:00","snow":{"3h":1.07},"weather":[{"icon":"13n","description":"light snow","main":"Snow","id":600}],"main":{"temp":271.46,"temp_min":271.46,"grnd_level":985,"temp_kf":0,"humidity":98,"pressure":1002,"sea_level":1002,"feels_like":266.04,"temp_max":271.46},"clouds":{"all":98},"sys":{"pod":"n"},"wind":{"deg":249,"speed":4.52}},{"dt":1611327600,"pop":0.62,"visibility":2711,"dt_txt":"2021-01-22 15:00:00","snow":{"3h":0.28},"weather":[{"icon":"13d","description":"light snow","main":"Snow","id":600}],"main":{"temp":272.45,"temp_min":272.45,"grnd_level":987,"temp_kf":0,"humidity":97,"pressure":1004,"sea_level":1004,"feels_like":266.47,"temp_max":272.45},"clouds":{"all":97},"sys":{"pod":"d"},"wind":{"deg":252,"speed":5.48}},{"dt":1611338400,"pop":0.85,"visibility":10000,"dt_txt":"2021-01-22 18:00:00","snow":{"3h":0.63},"weather":[{"icon":"13d","description":"light snow","main":"Snow","id":600}],"main":{"temp":272.56,"temp_min":272.56,"grnd_level":988,"temp_kf":0,"humidity":95,"pressure":1005,"sea_level":1005,"feels_like":266.16,"temp_max":272.56},"clouds":{"all":98},"sys":{"pod":"d"},"wind":{"deg":303,"speed":6.05}},{"dt":1611349200,"pop":0.93,"visibility":7674,"dt_txt":"2021-01-22 21:00:00","snow":{"3h":1.62},"weather":[{"icon":"13d","description":"snow","main":"Snow","id":601}],"main":{"temp":270.6,"temp_min":270.6,"grnd_level":990,"temp_kf":0,"humidity":95,"pressure":1007,"sea_level":1007,"feels_like":264.04,"temp_max":270.6},"clouds":{"all":97},"sys":{"pod":"d"},"wind":{"deg":293,"speed":5.92}},{"dt":1611360000,"pop":0.86,"visibility":10000,"dt_txt":"2021-01-23 00:00:00","snow":{"3h":0.11},"weather":[{"icon":"13n","description":"light snow","main":"Snow","id":600}],"main":{"temp":266.6,"temp_min":266.6,"grnd_level":993,"temp_kf":0,"humidity":94,"pressure":1011,"sea_level":1011,"feels_like":261,"temp_max":266.6},"clouds":{"all":93},"sys":{"pod":"n"},"wind":{"deg":298,"speed":3.95}},{"dt":1611370800,"pop":0.6,"visibility":6704,"dt_txt":"2021-01-23 03:00:00","weather":[{"icon":"04n","description":"broken clouds","main":"Clouds","id":803}],"main":{"temp":265.4,"temp_min":265.4,"grnd_level":995,"temp_kf":0,"humidity":95,"pressure":1013,"sea_level":1013,"feels_like":259.51,"temp_max":265.4},"clouds":{"all":58},"sys":{"pod":"n"},"wind":{"deg":293,"speed":4.23}},{"dt":1611381600,"pop":0.6,"visibility":10000,"dt_txt":"2021-01-23 06:00:00","snow":{"3h":0.15},"weather":[{"icon":"13n","description":"light snow","main":"Snow","id":600}],"main":{"temp":263.66,"temp_min":263.66,"grnd_level":996,"temp_kf":0,"humidity":95,"pressure":1014,"sea_level":1014,"feels_like":257.78,"temp_max":263.66},"clouds":{"all":72},"sys":{"pod":"n"},"wind":{"deg":300,"speed":4.02}},{"dt":1611392400,"pop":0.37,"visibility":9022,"dt_txt":"2021-01-23 09:00:00","weather":[{"icon":"04n","description":"broken clouds","main":"Clouds","id":803}],"main":{"temp":261.95,"temp_min":261.95,"grnd_level":998,"temp_kf":0,"humidity":94,"pressure":1016,"sea_level":1016,"feels_like":256.1,"temp_max":261.95},"clouds":{"all":79},"sys":{"pod":"n"},"wind":{"deg":306,"speed":3.79}},{"dt":1611403200,"pop":0.37,"visibility":4708,"dt_txt":"2021-01-23 12:00:00","snow":{"3h":0.1},"weather":[{"icon":"13n","description":"light snow","main":"Snow","id":600}],"main":{"temp":259.82,"temp_min":259.82,"grnd_level":1000,"temp_kf":0,"humidity":93,"pressure":1018,"sea_level":1018,"feels_like":254.2,"temp_max":259.82},"clouds":{"all":87},"sys":{"pod":"n"},"wind":{"deg":327,"speed":3.27}},{"dt":1611414000,"pop":0.26,"visibility":9851,"dt_txt":"2021-01-23 15:00:00","weather":[{"icon":"04d","description":"overcast clouds","main":"Clouds","id":804}],"main":{"temp":262.21,"temp_min":262.21,"grnd_level":1002,"temp_kf":0,"humidity":92,"pressure":1020,"sea_level":1020,"feels_like":255.38,"temp_max":262.21},"clouds":{"all":87},"sys":{"pod":"d"},"wind":{"deg":314,"speed":5.2}},{"dt":1611424800,"pop":0.26,"visibility":6798,"dt_txt":"2021-01-23 18:00:00","weather":[{"icon":"04d","description":"overcast clouds","main":"Clouds","id":804}],"main":{"temp":264.32,"temp_min":264.32,"grnd_level":1003,"temp_kf":0,"humidity":92,"pressure":1020,"sea_level":1020,"feels_like":256.42,"temp_max":264.32},"clouds":{"all":94},"sys":{"pod":"d"},"wind":{"deg":298,"speed":6.93}},{"dt":1611435600,"pop":0,"visibility":8280,"dt_txt":"2021-01-23 21:00:00","weather":[{"icon":"04d","description":"overcast clouds","main":"Clouds","id":804}],"main":{"temp":263.67,"temp_min":263.67,"grnd_level":1003,"temp_kf":0,"humidity":93,"pressure":1021,"sea_level":1021,"feels_like":256.15,"temp_max":263.67},"clouds":{"all":100},"sys":{"pod":"d"},"wind":{"deg":300,"speed":6.33}},{"dt":1611446400,"pop":0,"visibility":10000,"dt_txt":"2021-01-24 00:00:00","weather":[{"icon":"04n","description":"overcast clouds","main":"Clouds","id":804}],"main":{"temp":262.48,"temp_min":262.48,"grnd_level":1005,"temp_kf":0,"humidity":92,"pressure":1023,"sea_level":1023,"feels_like":256.28,"temp_max":262.48},"clouds":{"all":100},"sys":{"pod":"n"},"wind":{"deg":304,"speed":4.32}},{"dt":1611457200,"pop":0,"visibility":10000,"dt_txt":"2021-01-24 03:00:00","weather":[{"icon":"04n","description":"broken clouds","main":"Clouds","id":803}],"main":{"temp":260.39,"temp_min":260.39,"grnd_level":1006,"temp_kf":0,"humidity":92,"pressure":1024,"sea_level":1024,"feels_like":254.67,"temp_max":260.39},"clouds":{"all":59},"sys":{"pod":"n"},"wind":{"deg":320,"speed":3.45}},{"dt":1611468000,"pop":0,"visibility":10000,"dt_txt":"2021-01-24 06:00:00","weather":[{"icon":"03n","description":"scattered clouds","main":"Clouds","id":802}],"main":{"temp":258.34,"temp_min":258.34,"grnd_level":1006,"temp_kf":0,"humidity":91,"pressure":1024,"sea_level":1024,"feels_like":252.74,"temp_max":258.34},"clouds":{"all":47},"sys":{"pod":"n"},"wind":{"deg":320,"speed":3.12}},{"dt":1611478800,"pop":0,"visibility":10000,"dt_txt":"2021-01-24 09:00:00","weather":[{"icon":"02n","description":"few clouds","main":"Clouds","id":801}],"main":{"temp":256.97,"temp_min":256.97,"grnd_level":1005,"temp_kf":0,"humidity":91,"pressure":1024,"sea_level":1024,"feels_like":251.77,"temp_max":256.97},"clouds":{"all":24},"sys":{"pod":"n"},"wind":{"deg":320,"speed":2.46}},{"dt":1611489600,"pop":0,"visibility":10000,"dt_txt":"2021-01-24 12:00:00","weather":[{"icon":"02n","description":"few clouds","main":"Clouds","id":801}],"main":{"temp":256.7,"temp_min":256.7,"grnd_level":1006,"temp_kf":0,"humidity":90,"pressure":1024,"sea_level":1024,"feels_like":251.76,"temp_max":256.7},"clouds":{"all":19},"sys":{"pod":"n"},"wind":{"deg":324,"speed":2.06}},{"dt":1611500400,"pop":0,"visibility":10000,"dt_txt":"2021-01-24 15:00:00","weather":[{"icon":"02d","description":"few clouds","main":"Clouds","id":801}],"main":{"temp":262.72,"temp_min":262.72,"grnd_level":1005,"temp_kf":0,"humidity":90,"pressure":1023,"sea_level":1023,"feels_like":257.32,"temp_max":262.72},"clouds":{"all":13},"sys":{"pod":"d"},"wind":{"deg":309,"speed":3.17}},{"dt":1611511200,"pop":0,"visibility":10000,"dt_txt":"2021-01-24 18:00:00","weather":[{"icon":"03d","description":"scattered clouds","main":"Clouds","id":802}],"main":{"temp":265.65,"temp_min":265.65,"grnd_level":1003,"temp_kf":0,"humidity":90,"pressure":1021,"sea_level":1021,"feels_like":259.49,"temp_max":265.65},"clouds":{"all":32},"sys":{"pod":"d"},"wind":{"deg":294,"speed":4.56}},{"dt":1611522000,"pop":0,"visibility":10000,"dt_txt":"2021-01-24 21:00:00","weather":[{"icon":"04d","description":"overcast clouds","main":"Clouds","id":804}],"main":{"temp":265.24,"temp_min":265.24,"grnd_level":1003,"temp_kf":0,"humidity":92,"pressure":1020,"sea_level":1020,"feels_like":259.85,"temp_max":265.24},"clouds":{"all":100},"sys":{"pod":"d"},"wind":{"deg":295,"speed":3.44}},{"dt":1611532800,"pop":0,"visibility":10000,"dt_txt":"2021-01-25 00:00:00","weather":[{"icon":"04n","description":"overcast clouds","main":"Clouds","id":804}],"main":{"temp":261.81,"temp_min":261.81,"grnd_level":1004,"temp_kf":0,"humidity":93,"pressure":1021,"sea_level":1021,"feels_like":257.33,"temp_max":261.81},"clouds":{"all":93},"sys":{"pod":"n"},"wind":{"deg":320,"speed":1.81}},{"dt":1611543600,"pop":0,"visibility":10000,"dt_txt":"2021-01-25 03:00:00","weather":[{"icon":"01n","description":"clear sky","main":"Clear","id":800}],"main":{"temp":259.55,"temp_min":259.55,"grnd_level":1003,"temp_kf":0,"humidity":90,"pressure":1021,"sea_level":1021,"feels_like":255.36,"temp_max":259.55},"clouds":{"all":7},"sys":{"pod":"n"},"wind":{"deg":4,"speed":1.18}},{"dt":1611554400,"pop":0,"visibility":10000,"dt_txt":"2021-01-25 06:00:00","weather":[{"icon":"01n","description":"clear sky","main":"Clear","id":800}],"main":{"temp":258.26,"temp_min":258.26,"grnd_level":1003,"temp_kf":0,"humidity":89,"pressure":1021,"sea_level":1021,"feels_like":254.13,"temp_max":258.26},"clouds":{"all":4},"sys":{"pod":"n"},"wind":{"deg":37,"speed":0.99}},{"dt":1611565200,"pop":0,"visibility":10000,"dt_txt":"2021-01-25 09:00:00","weather":[{"icon":"01n","description":"clear sky","main":"Clear","id":800}],"main":{"temp":257.27,"temp_min":257.27,"grnd_level":1003,"temp_kf":0,"humidity":89,"pressure":1021,"sea_level":1021,"feels_like":253.24,"temp_max":257.27},"clouds":{"all":8},"sys":{"pod":"n"},"wind":{"deg":43,"speed":0.79}},{"dt":1611576000,"pop":0,"visibility":10000,"dt_txt":"2021-01-25 12:00:00","weather":[{"icon":"01n","description":"clear sky","main":"Clear","id":800}],"main":{"temp":256.56,"temp_min":256.56,"grnd_level":1003,"temp_kf":0,"humidity":88,"pressure":1022,"sea_level":1022,"feels_like":252.63,"temp_max":256.56},"clouds":{"all":6},"sys":{"pod":"n"},"wind":{"deg":45,"speed":0.59}},{"dt":1611586800,"pop":0,"visibility":10000,"dt_txt":"2021-01-25 15:00:00","weather":[{"icon":"01d","description":"clear sky","main":"Clear","id":800}],"main":{"temp":262.62,"temp_min":262.62,"grnd_level":1004,"temp_kf":0,"humidity":90,"pressure":1022,"sea_level":1022,"feels_like":258.93,"temp_max":262.62},"clouds":{"all":0},"sys":{"pod":"d"},"wind":{"deg":298,"speed":0.72}},{"dt":1611597600,"pop":0,"visibility":10000,"dt_txt":"2021-01-25 18:00:00","weather":[{"icon":"01d","description":"clear sky","main":"Clear","id":800}],"main":{"temp":267.49,"temp_min":267.49,"grnd_level":1002,"temp_kf":0,"humidity":90,"pressure":1019,"sea_level":1019,"feels_like":263.66,"temp_max":267.49},"clouds":{"all":3},"sys":{"pod":"d"},"wind":{"deg":272,"speed":1.45}},{"dt":1611608400,"pop":0,"visibility":10000,"dt_txt":"2021-01-25 21:00:00","weather":[{"icon":"04d","description":"broken clouds","main":"Clouds","id":803}],"main":{"temp":266.8,"temp_min":266.8,"grnd_level":1001,"temp_kf":0,"humidity":94,"pressure":1019,"sea_level":1019,"feels_like":263.24,"temp_max":266.8},"clouds":{"all":68},"sys":{"pod":"d"},"wind":{"deg":229,"speed":1.06}},{"dt":1611619200,"pop":0,"visibility":10000,"dt_txt":"2021-01-26 00:00:00","weather":[{"icon":"04n","description":"broken clouds","main":"Clouds","id":803}],"main":{"temp":261.71,"temp_min":261.71,"grnd_level":1001,"temp_kf":0,"humidity":92,"pressure":1019,"sea_level":1019,"feels_like":257.57,"temp_max":261.71},"clouds":{"all":66},"sys":{"pod":"n"},"wind":{"deg":30,"speed":1.31}},{"dt":1611630000,"pop":0,"visibility":10000,"dt_txt":"2021-01-26 03:00:00","weather":[{"icon":"04n","description":"overcast clouds","main":"Clouds","id":804}],"main":{"temp":260.21,"temp_min":260.21,"grnd_level":1001,"temp_kf":0,"humidity":91,"pressure":1019,"sea_level":1019,"feels_like":256.21,"temp_max":260.21},"clouds":{"all":100},"sys":{"pod":"n"},"wind":{"deg":27,"speed":0.97}},{"dt":1611640800,"pop":0,"visibility":10000,"dt_txt":"2021-01-26 06:00:00","weather":[{"icon":"04n","description":"overcast clouds","main":"Clouds","id":804}],"main":{"temp":258.77,"temp_min":258.77,"grnd_level":1000,"temp_kf":0,"humidity":89,"pressure":1018,"sea_level":1018,"feels_like":254.62,"temp_max":258.77},"clouds":{"all":86},"sys":{"pod":"n"},"wind":{"deg":30,"speed":1.05}},{"dt":1611651600,"pop":0,"visibility":10000,"dt_txt":"2021-01-26 09:00:00","weather":[{"icon":"04n","description":"overcast clouds","main":"Clouds","id":804}],"main":{"temp":258.88,"temp_min":258.88,"grnd_level":998,"temp_kf":0,"humidity":88,"pressure":1016,"sea_level":1016,"feels_like":254.57,"temp_max":258.88},"clouds":{"all":99},"sys":{"pod":"n"},"wind":{"deg":34,"speed":1.28}},{"dt":1611662400,"pop":0,"visibility":10000,"dt_txt":"2021-01-26 12:00:00","weather":[{"icon":"04n","description":"overcast clouds","main":"Clouds","id":804}],"main":{"temp":258.97,"temp_min":258.97,"grnd_level":1000,"temp_kf":0,"humidity":88,"pressure":1018,"sea_level":1018,"feels_like":255.12,"temp_max":258.97},"clouds":{"all":99},"sys":{"pod":"n"},"wind":{"deg":14,"speed":0.63}}]},{"city":{"country":"GB","coord":{"lon":-0.0918,"lat":51.5128},"sunrise":1611215595,"timezone":0,"sunset":1611246588,"name":"City of London","id":2643741,"population":7556900},"cnt":40,"cod":"200","message":0,"list":[{"dt":1611241200,"pop":0.14,"visibility":10000,"dt_txt":"2021-01-21 15:00:00","weather":[{"icon":"03d","description":"scattered clouds","main":"Clouds","id":802}],"main":{"temp":281.46,"temp_min":281.46,"grnd_level":982,"temp_kf":-0.08,"humidity":60,"pressure":986,"sea_level":986,"feels_like":276.08,"temp_max":281.54},"clouds":{"all":50},"sys":{"pod":"d"},"wind":{"deg":236,"speed":5.07}},{"dt":1611252000,"pop":0.22,"rain":{"3h":0.16},"visibility":10000,"dt_txt":"2021-01-21 18:00:00","weather":[{"icon":"10n","description":"light rain","main":"Rain","id":500}],"main":{"temp":280.48,"temp_min":280.23,"grnd_level":981,"temp_kf":0.25,"humidity":69,"pressure":984,"sea_level":984,"feels_like":277.27,"temp_max":280.48},"clouds":{"all":75},"sys":{"pod":"n"},"wind":{"deg":223,"speed":2.2}},{"dt":1611262800,"pop":0.35,"rain":{"3h":0.13},"visibility":10000,"dt_txt":"2021-01-21 21:00:00","weather":[{"icon":"10n","description":"light rain","main":"Rain","id":500}],"main":{"temp":279.6,"temp_min":279.48,"grnd_level":982,"temp_kf":0.12,"humidity":69,"pressure":985,"sea_level":985,"feels_like":275.25,"temp_max":279.6},"clouds":{"all":95},"sys":{"pod":"n"},"wind":{"deg":282,"speed":3.63}},{"dt":1611273600,"pop":0.02,"visibility":10000,"dt_txt":"2021-01-22 00:00:00","weather":[{"icon":"04n","description":"broken clouds","main":"Clouds","id":803}],"main":{"temp":277.63,"temp_min":277.6,"grnd_level":984,"temp_kf":0.03,"humidity":74,"pressure":987,"sea_level":987,"feels_like":273.02,"temp_max":277.63},"clouds":{"all":78},"sys":{"pod":"n"},"wind":{"deg":283,"speed":3.8}},{"dt":1611284400,"pop":0,"visibility":10000,"dt_txt":"2021-01-22 03:00:00","weather":[{"icon":"01n","description":"clear sky","main":"Clear","id":800}],"main":{"temp":276.8,"temp_min":276.8,"grnd_level":985,"temp_kf":0,"humidity":76,"pressure":988,"sea_level":988,"feels_like":272.25,"temp_max":276.8},"clouds":{"all":0},"sys":{"pod":"n"},"wind":{"deg":268,"speed":3.63}},{"dt":1611295200,"pop":0,"visibility":10000,"dt_txt":"2021-01-22 06:00:00","weather":[{"icon":"01n","description":"clear sky","main":"Clear","id":800}],"main":{"temp":276.2,"temp_min":276.2,"grnd_level":987,"temp_kf":0,"humidity":80,"pressure":990,"sea_level":990,"feels_like":272.14,"temp_max":276.2},"clouds":{"all":0},"sys":{"pod":"n"},"wind":{"deg":255,"speed":2.95}},{"dt":1611306000,"pop":0,"visibility":10000,"dt_txt":"2021-01-22 09:00:00","weather":[{"icon":"01d","description":"clear sky","main":"Clear","id":800}],"main":{"temp":276.06,"temp_min":276.06,"grnd_level":988,"temp_kf":0,"humidity":80,"pressure":992,"sea_level":992,"feels_like":271.96,"temp_max":276.06},"clouds":{"all":0},"sys":{"pod":"d"},"wind":{"deg":250,"speed":2.98}},{"dt":1611316800,"pop":0,"visibility":10000,"dt_txt":"2021-01-22 12:00:00","weather":[{"icon":"01d","description":"clear sky","main":"Clear","id":800}],"main":{"temp":278.68,"temp_min":278.68,"grnd_level":990,"temp_kf":0,"humidity":66,"pressure":993,"sea_level":993,"feels_like":274.61,"temp_max":278.68},"clouds":{"all":0},"sys":{"pod":"d"},"wind":{"deg":261,"speed":2.91}},{"dt":1611327600,"pop":0,"visibility":10000,"dt_txt":"2021-01-22 15:00:00","weather":[{"icon":"01d","description":"clear sky","main":"Clear","id":800}],"main":{"temp":279.35,"temp_min":279.35,"grnd_level":990,"temp_kf":0,"humidity":63,"pressure":993,"sea_level":993,"feels_like":275.6,"temp_max":279.35},"clouds":{"all":1},"sys":{"pod":"d"},"wind":{"deg":262,"speed":2.45}},{"dt":1611338400,"pop":0,"visibility":10000,"dt_txt":"2021-01-22 18:00:00","weather":[{"icon":"03n","description":"scattered clouds","main":"Clouds","id":802}],"main":{"temp":277.59,"temp_min":277.59,"grnd_level":990,"temp_kf":0,"humidity":72,"pressure":994,"sea_level":994,"feels_like":274.8,"temp_max":277.59},"clouds":{"all":29},"sys":{"pod":"n"},"wind":{"deg":239,"speed":1.11}},{"dt":1611349200,"pop":0,"visibility":10000,"dt_txt":"2021-01-22 21:00:00","weather":[{"icon":"04n","description":"overcast clouds","main":"Clouds","id":804}],"main":{"temp":276.88,"temp_min":276.88,"grnd_level":991,"temp_kf":0,"humidity":76,"pressure":994,"sea_level":994,"feels_like":274.39,"temp_max":276.88},"clouds":{"all":96},"sys":{"pod":"n"},"wind":{"deg":212,"speed":0.7}},{"dt":1611360000,"pop":0.02,"visibility":10000,"dt_txt":"2021-01-23 00:00:00","weather":[{"icon":"04n","description":"overcast clouds","main":"Clouds","id":804}],"main":{"temp":276.49,"temp_min":276.49,"grnd_level":990,"temp_kf":0,"humidity":78,"pressure":994,"sea_level":994,"feels_like":273.77,"temp_max":276.49},"clouds":{"all":98},"sys":{"pod":"n"},"wind":{"deg":18,"speed":1.03}},{"dt":1611370800,"pop":0.02,"visibility":10000,"dt_txt":"2021-01-23 03:00:00","weather":[{"icon":"04n","description":"overcast clouds","main":"Clouds","id":804}],"main":{"temp":275.73,"temp_min":275.73,"grnd_level":990,"temp_kf":0,"humidity":82,"pressure":993,"sea_level":993,"feels_like":272.58,"temp_max":275.73},"clouds":{"all":100},"sys":{"pod":"n"},"wind":{"deg":341,"speed":1.62}},{"dt":1611381600,"pop":0.02,"visibility":10000,"dt_txt":"2021-01-23 06:00:00","weather":[{"icon":"04n","description":"broken clouds","main":"Clouds","id":803}],"main":{"temp":274.86,"temp_min":274.86,"grnd_level":991,"temp_kf":0,"humidity":86,"pressure":994,"sea_level":994,"feels_like":271.56,"temp_max":274.86},"clouds":{"all":62},"sys":{"pod":"n"},"wind":{"deg":328,"speed":1.8}},{"dt":1611392400,"pop":0,"visibility":10000,"dt_txt":"2021-01-23 09:00:00","weather":[{"icon":"04d","description":"overcast clouds","main":"Clouds","id":804}],"main":{"temp":274.93,"temp_min":274.93,"grnd_level":992,"temp_kf":0,"humidity":84,"pressure":995,"sea_level":995,"feels_like":271.36,"temp_max":274.93},"clouds":{"all":100},"sys":{"pod":"d"},"wind":{"deg":318,"speed":2.13}},{"dt":1611403200,"pop":0,"visibility":10000,"dt_txt":"2021-01-23 12:00:00","weather":[{"icon":"04d","description":"overcast clouds","main":"Clouds","id":804}],"main":{"temp":276.7,"temp_min":276.7,"grnd_level":994,"temp_kf":0,"humidity":74,"pressure":997,"sea_level":997,"feels_like":272.79,"temp_max":276.7},"clouds":{"all":100},"sys":{"pod":"d"},"wind":{"deg":298,"speed":2.62}},{"dt":1611414000,"pop":0,"visibility":10000,"dt_txt":"2021-01-23 15:00:00","weather":[{"icon":"04d","description":"overcast clouds","main":"Clouds","id":804}],"main":{"temp":276.95,"temp_min":276.95,"grnd_level":994,"temp_kf":0,"humidity":74,"pressure":997,"sea_level":997,"feels_like":272.92,"temp_max":276.95},"clouds":{"all":100},"sys":{"pod":"d"},"wind":{"deg":318,"speed":2.84}},{"dt":1611424800,"pop":0.2,"rain":{"3h":0.14},"visibility":10000,"dt_txt":"2021-01-23 18:00:00","weather":[{"icon":"10n","description":"light rain","main":"Rain","id":500}],"main":{"temp":275.85,"temp_min":275.85,"grnd_level":995,"temp_kf":0,"humidity":79,"pressure":998,"sea_level":998,"feels_like":272.52,"temp_max":275.85},"clouds":{"all":100},"sys":{"pod":"n"},"wind":{"deg":291,"speed":1.8}},{"dt":1611435600,"pop":0,"visibility":10000,"dt_txt":"2021-01-23 21:00:00","weather":[{"icon":"01n","description":"clear sky","main":"Clear","id":800}],"main":{"temp":274.68,"temp_min":274.68,"grnd_level":995,"temp_kf":0,"humidity":85,"pressure":999,"sea_level":999,"feels_like":271.35,"temp_max":274.68},"clouds":{"all":1},"sys":{"pod":"n"},"wind":{"deg":290,"speed":1.77}},{"dt":1611446400,"pop":0,"visibility":10000,"dt_txt":"2021-01-24 00:00:00","weather":[{"icon":"01n","description":"clear sky","main":"Clear","id":800}],"main":{"temp":273.89,"temp_min":273.89,"grnd_level":996,"temp_kf":0,"humidity":89,"pressure":999,"sea_level":999,"feels_like":270.99,"temp_max":273.89},"clouds":{"all":1},"sys":{"pod":"n"},"wind":{"deg":243,"speed":1.13}},{"dt":1611457200,"pop":0,"visibility":10000,"dt_txt":"2021-01-24 03:00:00","weather":[{"icon":"01n","description":"clear sky","main":"Clear","id":800}],"main":{"temp":273.29,"temp_min":273.29,"grnd_level":995,"temp_kf":0,"humidity":92,"pressure":998,"sea_level":998,"feels_like":270.39,"temp_max":273.29},"clouds":{"all":0},"sys":{"pod":"n"},"wind":{"deg":210,"speed":1.1}},{"dt":1611468000,"pop":0,"visibility":10000,"dt_txt":"2021-01-24 06:00:00","weather":[{"icon":"03n","description":"scattered clouds","main":"Clouds","id":802}],"main":{"temp":273.27,"temp_min":273.27,"grnd_level":995,"temp_kf":0,"humidity":91,"pressure":998,"sea_level":998,"feels_like":270.4,"temp_max":273.27},"clouds":{"all":27},"sys":{"pod":"n"},"wind":{"deg":149,"speed":1.03}},{"dt":1611478800,"pop":0,"visibility":10000,"dt_txt":"2021-01-24 09:00:00","weather":[{"icon":"04d","description":"overcast clouds","main":"Clouds","id":804}],"main":{"temp":273.62,"temp_min":273.62,"grnd_level":994,"temp_kf":0,"humidity":89,"pressure":998,"sea_level":998,"feels_like":271.03,"temp_max":273.62},"clouds":{"all":97},"sys":{"pod":"d"},"wind":{"deg":111,"speed":0.63}},{"dt":1611489600,"pop":0.02,"visibility":10000,"dt_txt":"2021-01-24 12:00:00","weather":[{"icon":"04d","description":"broken clouds","main":"Clouds","id":803}],"main":{"temp":276.37,"temp_min":276.37,"grnd_level":994,"temp_kf":0,"humidity":73,"pressure":998,"sea_level":998,"feels_like":273.26,"temp_max":276.37},"clouds":{"all":63},"sys":{"pod":"d"},"wind":{"deg":95,"speed":1.37}},{"dt":1611500400,"pop":0.32,"visibility":10000,"dt_txt":"2021-01-24 15:00:00","weather":[{"icon":"04d","description":"overcast clouds","main":"Clouds","id":804}],"main":{"temp":276.89,"temp_min":276.89,"grnd_level":995,"temp_kf":0,"humidity":72,"pressure":999,"sea_level":999,"feels_like":274.01,"temp_max":276.89},"clouds":{"all":94},"sys":{"pod":"d"},"wind":{"deg":24,"speed":1.11}},{"dt":1611511200,"pop":0.3,"visibility":10000,"dt_txt":"2021-01-24 18:00:00","weather":[{"icon":"04n","description":"overcast clouds","main":"Clouds","id":804}],"main":{"temp":275.61,"temp_min":275.61,"grnd_level":998,"temp_kf":0,"humidity":78,"pressure":1001,"sea_level":1001,"feels_like":272.12,"temp_max":275.61},"clouds":{"all":96},"sys":{"pod":"n"},"wind":{"deg":288,"speed":1.95}},{"dt":1611522000,"pop":0.03,"visibility":10000,"dt_txt":"2021-01-24 21:00:00","weather":[{"icon":"03n","description":"scattered clouds","main":"Clouds","id":802}],"main":{"temp":274.58,"temp_min":274.58,"grnd_level":999,"temp_kf":0,"humidity":87,"pressure":1002,"sea_level":1002,"feels_like":270.12,"temp_max":274.58},"clouds":{"all":49},"sys":{"pod":"n"},"wind":{"deg":245,"speed":3.43}},{"dt":1611532800,"pop":0,"visibility":10000,"dt_txt":"2021-01-25 00:00:00","weather":[{"icon":"04n","description":"broken clouds","main":"Clouds","id":803}],"main":{"temp":274.58,"temp_min":274.58,"grnd_level":999,"temp_kf":0,"humidity":86,"pressure":1003,"sea_level":1003,"feels_like":269.32,"temp_max":274.58},"clouds":{"all":56},"sys":{"pod":"n"},"wind":{"deg":235,"speed":4.54}},{"dt":1611543600,"pop":0.44,"visibility":10000,"dt_txt":"2021-01-25 03:00:00","snow":{"3h":0.22},"weather":[{"icon":"13n","description":"light snow","main":"Snow","id":600}],"main":{"temp":275.53,"temp_min":275.53,"grnd_level":999,"temp_kf":0,"humidity":84,"pressure":1003,"sea_level":1003,"feels_like":270.02,"temp_max":275.53},"clouds":{"all":70},"sys":{"pod":"n"},"wind":{"deg":258,"speed":5.02}},{"dt":1611554400,"pop":0.35,"visibility":10000,"dt_txt":"2021-01-25 06:00:00","weather":[{"icon":"04n","description":"broken clouds","main":"Clouds","id":803}],"main":{"temp":275.67,"temp_min":275.67,"grnd_level":1001,"temp_kf":0,"humidity":88,"pressure":1004,"sea_level":1004,"feels_like":269.79,"temp_max":275.67},"clouds":{"all":84},"sys":{"pod":"n"},"wind":{"deg":290,"speed":5.72}},{"dt":1611565200,"pop":0,"visibility":10000,"dt_txt":"2021-01-25 09:00:00","weather":[{"icon":"04d","description":"broken clouds","main":"Clouds","id":803}],"main":{"temp":275.41,"temp_min":275.41,"grnd_level":1004,"temp_kf":0,"humidity":83,"pressure":1007,"sea_level":1007,"feels_like":270.57,"temp_max":275.41},"clouds":{"all":78},"sys":{"pod":"d"},"wind":{"deg":295,"speed":4.01}},{"dt":1611576000,"pop":0,"visibility":10000,"dt_txt":"2021-01-25 12:00:00","weather":[{"icon":"03d","description":"scattered clouds","main":"Clouds","id":802}],"main":{"temp":277.57,"temp_min":277.57,"grnd_level":1006,"temp_kf":0,"humidity":75,"pressure":1009,"sea_level":1009,"feels_like":272.77,"temp_max":277.57},"clouds":{"all":42},"sys":{"pod":"d"},"wind":{"deg":278,"speed":4.1}},{"dt":1611586800,"pop":0,"visibility":10000,"dt_txt":"2021-01-25 15:00:00","weather":[{"icon":"04d","description":"overcast clouds","main":"Clouds","id":804}],"main":{"temp":277.94,"temp_min":277.94,"grnd_level":1006,"temp_kf":0,"humidity":71,"pressure":1009,"sea_level":1009,"feels_like":272.65,"temp_max":277.94},"clouds":{"all":95},"sys":{"pod":"d"},"wind":{"deg":275,"speed":4.72}},{"dt":1611597600,"pop":0,"visibility":10000,"dt_txt":"2021-01-25 18:00:00","weather":[{"icon":"04n","description":"overcast clouds","main":"Clouds","id":804}],"main":{"temp":277.05,"temp_min":277.05,"grnd_level":1008,"temp_kf":0,"humidity":74,"pressure":1011,"sea_level":1011,"feels_like":271.93,"temp_max":277.05},"clouds":{"all":94},"sys":{"pod":"n"},"wind":{"deg":273,"speed":4.41}},{"dt":1611608400,"pop":0,"visibility":10000,"dt_txt":"2021-01-25 21:00:00","weather":[{"icon":"01n","description":"clear sky","main":"Clear","id":800}],"main":{"temp":275.57,"temp_min":275.57,"grnd_level":1010,"temp_kf":0,"humidity":82,"pressure":1013,"sea_level":1013,"feels_like":270.95,"temp_max":275.57},"clouds":{"all":10},"sys":{"pod":"n"},"wind":{"deg":272,"speed":3.7}},{"dt":1611619200,"pop":0,"visibility":10000,"dt_txt":"2021-01-26 00:00:00","weather":[{"icon":"01n","description":"clear sky","main":"Clear","id":800}],"main":{"temp":274.66,"temp_min":274.66,"grnd_level":1011,"temp_kf":0,"humidity":87,"pressure":1014,"sea_level":1014,"feels_like":270.25,"temp_max":274.66},"clouds":{"all":5},"sys":{"pod":"n"},"wind":{"deg":260,"speed":3.38}},{"dt":1611630000,"pop":0,"visibility":10000,"dt_txt":"2021-01-26 03:00:00","weather":[{"icon":"03n","description":"scattered clouds","main":"Clouds","id":802}],"main":{"temp":274.17,"temp_min":274.17,"grnd_level":1011,"temp_kf":0,"humidity":89,"pressure":1014,"sea_level":1014,"feels_like":270.15,"temp_max":274.17},"clouds":{"all":41},"sys":{"pod":"n"},"wind":{"deg":247,"speed":2.78}},{"dt":1611640800,"pop":0,"visibility":10000,"dt_txt":"2021-01-26 06:00:00","weather":[{"icon":"04n","description":"broken clouds","main":"Clouds","id":803}],"main":{"temp":274.09,"temp_min":274.09,"grnd_level":1011,"temp_kf":0,"humidity":89,"pressure":1014,"sea_level":1014,"feels_like":270.68,"temp_max":274.09},"clouds":{"all":70},"sys":{"pod":"n"},"wind":{"deg":219,"speed":1.9}},{"dt":1611651600,"pop":0.43,"rain":{"3h":0.21},"visibility":10000,"dt_txt":"2021-01-26 09:00:00","weather":[{"icon":"10d","description":"light rain","main":"Rain","id":500}],"main":{"temp":275.52,"temp_min":275.52,"grnd_level":1010,"temp_kf":0,"humidity":82,"pressure":1013,"sea_level":1013,"feels_like":271.88,"temp_max":275.52},"clouds":{"all":100},"sys":{"pod":"d"},"wind":{"deg":168,"speed":2.28}},{"dt":1611662400,"pop":1,"rain":{"3h":2.62},"visibility":10000,"dt_txt":"2021-01-26 12:00:00","weather":[{"icon":"10d","description":"light rain","main":"Rain","id":500}],"main":{"temp":278.29,"temp_min":278.29,"grnd_level":1007,"temp_kf":0,"humidity":95,"pressure":1010,"sea_level":1010,"feels_like":274.63,"temp_max":278.29},"clouds":{"all":100},"sys":{"pod":"d"},"wind":{"deg":198,"speed":3.45}}]},{"city":{"country":"DE","coord":{"lon":13.4105,"lat":52.5244},"sunrise":1611212605,"timezone":3600,"sunset":1611243095,"name":"Berlin","id":2950159,"population":1000000},"cnt":40,"cod":"200","message":0,"list":[{"dt":1611241200,"pop":0.36,"rain":{"3h":0.25},"visibility":10000,"dt_txt":"2021-01-21 15:00:00","weather":[{"icon":"10d","description":"light rain","main":"Rain","id":500}],"main":{"temp":282.82,"temp_min":280.31,"grnd_level":992,"temp_kf":2.51,"humidity":65,"pressure":996,"sea_level":996,"feels_like":279.4,"temp_max":282.82},"clouds":{"all":87},"sys":{"pod":"d"},"wind":{"deg":187,"speed":2.85}},{"dt":1611252000,"pop":0,"visibility":10000,"dt_txt":"2021-01-21 18:00:00","weather":[{"icon":"04n","description":"overcast clouds","main":"Clouds","id":804}],"main":{"temp":280.97,"temp_min":279.8,"grnd_level":992,"temp_kf":1.17,"humidity":77,"pressure":997,"sea_level":997,"feels_like":276.54,"temp_max":280.97},"clouds":{"all":95},"sys":{"pod":"n"},"wind":{"deg":216,"speed":4.45}},{"dt":1611262800,"pop":0,"visibility":10000,"dt_txt":"2021-01-21 21:00:00","weather":[{"icon":"04n","description":"overcast clouds","main":"Clouds","id":804}],"main":{"temp":279.55,"temp_min":279.16,"grnd_level":992,"temp_kf":0.39,"humidity":71,"pressure":997,"sea_level":997,"feels_like":274.09,"temp_max":279.55},"clouds":{"all":98},"sys":{"pod":"n"},"wind":{"deg":203,"speed":5.3}},{"dt":1611273600,"pop":0.27,"rain":{"3h":0.48},"visibility":10000,"dt_txt":"2021-01-22 00:00:00","weather":[{"icon":"10n","description":"light rain","main":"Rain","id":500}],"main":{"temp":280.62,"temp_min":280.58,"grnd_level":989,"temp_kf":0.04,"humidity":84,"pressure":994,"sea_level":994,"feels_like":275.01,"temp_max":280.62},"clouds":{"all":100},"sys":{"pod":"n"},"wind":{"deg":178,"speed":6.39}},{"dt":1611284400,"pop":0.65,"rain":{"3h":0.14},"visibility":10000,"dt_txt":"2021-01-22 03:00:00","weather":[{"icon":"10n","description":"light rain","main":"Rain","id":500}],"main":{"temp":282.24,"temp_min":282.24,"grnd_level":987,"temp_kf":0,"humidity":70,"pressure":992,"sea_level":992,"feels_like":275.29,"temp_max":282.24},"clouds":{"all":100},"sys":{"pod":"n"},"wind":{"deg":201,"speed":8.02}},{"dt":1611295200,"pop":0.2,"visibility":10000,"dt_txt":"2021-01-22 06:00:00","weather":[{"icon":"04n","description":"overcast clouds","main":"Clouds","id":804}],"main":{"temp":281.08,"temp_min":281.08,"grnd_level":986,"temp_kf":0,"humidity":67,"pressure":991,"sea_level":991,"feels_like":274.5,"temp_max":281.08},"clouds":{"all":100},"sys":{"pod":"n"},"wind":{"deg":193,"speed":7.06}},{"dt":1611306000,"pop":0,"visibility":10000,"dt_txt":"2021-01-22 09:00:00","weather":[{"icon":"03d","description":"scattered clouds","main":"Clouds","id":802}],"main":{"temp":280.48,"temp_min":280.48,"grnd_level":985,"temp_kf":0,"humidity":68,"pressure":990,"sea_level":990,"feels_like":273.76,"temp_max":280.48},"clouds":{"all":29},"sys":{"pod":"d"},"wind":{"deg":193,"speed":7.16}},{"dt":1611316800,"pop":0.34,"rain":{"3h":0.31},"visibility":10000,"dt_txt":"2021-01-22 12:00:00","weather":[{"icon":"10d","description":"light rain","main":"Rain","id":500}],"main":{"temp":280.09,"temp_min":280.09,"grnd_level":987,"temp_kf":0,"humidity":80,"pressure":992,"sea_level":992,"feels_like":275.16,"temp_max":280.09},"clouds":{"all":65},"sys":{"pod":"d"},"wind":{"deg":282,"speed":5.08}},{"dt":1611327600,"pop":0,"visibility":10000,"dt_txt":"2021-01-22 15:00:00","weather":[{"icon":"04d","description":"overcast clouds","main":"Clouds","id":804}],"main":{"temp":278.85,"temp_min":278.85,"grnd_level":988,"temp_kf":0,"humidity":75,"pressure":993,"sea_level":993,"feels_like":275.63,"temp_max":278.85},"clouds":{"all":100},"sys":{"pod":"d"},"wind":{"deg":266,"speed":2.12}},{"dt":1611338400,"pop":0,"visibility":10000,"dt_txt":"2021-01-22 18:00:00","weather":[{"icon":"04n","description":"overcast clouds","main":"Clouds","id":804}],"main":{"temp":276.87,"temp_min":276.87,"grnd_level":990,"temp_kf":0,"humidity":84,"pressure":995,"sea_level":995,"feels_like":273.89,"temp_max":276.87},"clouds":{"all":100},"sys":{"pod":"n"},"wind":{"deg":243,"speed":1.7}},{"dt":1611349200,"pop":0,"visibility":10000,"dt_txt":"2021-01-22 21:00:00","weather":[{"icon":"04n","description":"overcast clouds","main":"Clouds","id":804}],"main":{"temp":275.7,"temp_min":275.7,"grnd_level":991,"temp_kf":0,"humidity":83,"pressure":997,"sea_level":997,"feels_like":272.46,"temp_max":275.7},"clouds":{"all":87},"sys":{"pod":"n"},"wind":{"deg":239,"speed":1.79}},{"dt":1611360000,"pop":0,"visibility":10000,"dt_txt":"2021-01-23 00:00:00","weather":[{"icon":"04n","description":"overcast clouds","main":"Clouds","id":804}],"main":{"temp":275.64,"temp_min":275.64,"grnd_level":992,"temp_kf":0,"humidity":83,"pressure":997,"sea_level":997,"feels_like":272.77,"temp_max":275.64},"clouds":{"all":93},"sys":{"pod":"n"},"wind":{"deg":324,"speed":1.24}},{"dt":1611370800,"pop":0,"visibility":10000,"dt_txt":"2021-01-23 03:00:00","weather":[{"icon":"04n","description":"overcast clouds","main":"Clouds","id":804}],"main":{"temp":275.65,"temp_min":275.65,"grnd_level":991,"temp_kf":0,"humidity":83,"pressure":997,"sea_level":997,"feels_like":272.43,"temp_max":275.65},"clouds":{"all":100},"sys":{"pod":"n"},"wind":{"deg":36,"speed":1.75}},{"dt":1611381600,"pop":0.25,"visibility":10000,"dt_txt":"2021-01-23 06:00:00","weather":[{"icon":"04n","description":"overcast clouds","main":"Clouds","id":804}],"main":{"temp":275.58,"temp_min":275.58,"grnd_level":990,"temp_kf":0,"humidity":83,"pressure":996,"sea_level":996,"feels_like":271.63,"temp_max":275.58},"clouds":{"all":100},"sys":{"pod":"n"},"wind":{"deg":27,"speed":2.77}},{"dt":1611392400,"pop":0.7,"visibility":9863,"dt_txt":"2021-01-23 09:00:00","snow":{"3h":1.25},"weather":[{"icon":"13d","description":"light snow","main":"Snow","id":600}],"main":{"temp":274.81,"temp_min":274.81,"grnd_level":989,"temp_kf":0,"humidity":91,"pressure":994,"sea_level":994,"feels_like":270.48,"temp_max":274.81},"clouds":{"all":100},"sys":{"pod":"d"},"wind":{"deg":17,"speed":3.42}},{"dt":1611403200,"pop":0.98,"visibility":7545,"dt_txt":"2021-01-23 12:00:00","snow":{"3h":3.76},"weather":[{"icon":"13d","description":"snow","main":"Snow","id":601}],"main":{"temp":274.57,"temp_min":274.57,"grnd_level":988,"temp_kf":0,"humidity":93,"pressure":993,"sea_level":993,"feels_like":268.29,"temp_max":274.57},"clouds":{"all":100},"sys":{"pod":"d"},"wind":{"deg":343,"speed":6.22}},{"dt":1611414000,"pop":1,"visibility":41,"dt_txt":"2021-01-23 15:00:00","snow":{"3h":4.61},"weather":[{"icon":"13d","description":"snow","main":"Snow","id":601}],"main":{"temp":274.05,"temp_min":274.05,"grnd_level":988,"temp_kf":0,"humidity":96,"pressure":993,"sea_level":993,"feels_like":267.71,"temp_max":274.05},"clouds":{"all":100},"sys":{"pod":"d"},"wind":{"deg":313,"speed":6.29}},{"dt":1611424800,"pop":1,"visibility":10000,"dt_txt":"2021-01-23 18:00:00","snow":{"3h":0.69},"weather":[{"icon":"13n","description":"light snow","main":"Snow","id":600}],"main":{"temp":274.84,"temp_min":274.84,"grnd_level":989,"temp_kf":0,"humidity":88,"pressure":994,"sea_level":994,"feels_like":269.71,"temp_max":274.84},"clouds":{"all":100},"sys":{"pod":"n"},"wind":{"deg":306,"speed":4.47}},{"dt":1611435600,"pop":0,"visibility":10000,"dt_txt":"2021-01-23 21:00:00","weather":[{"icon":"04n","description":"overcast clouds","main":"Clouds","id":804}],"main":{"temp":273.82,"temp_min":273.82,"grnd_level":990,"temp_kf":0,"humidity":94,"pressure":996,"sea_level":996,"feels_like":269.64,"temp_max":273.82},"clouds":{"all":99},"sys":{"pod":"n"},"wind":{"deg":285,"speed":3.09}},{"dt":1611446400,"pop":0,"visibility":10000,"dt_txt":"2021-01-24 00:00:00","weather":[{"icon":"04n","description":"overcast clouds","main":"Clouds","id":804}],"main":{"temp":272.92,"temp_min":272.92,"grnd_level":992,"temp_kf":0,"humidity":98,"pressure":997,"sea_level":997,"feels_like":269.62,"temp_max":272.92},"clouds":{"all":100},"sys":{"pod":"n"},"wind":{"deg":268,"speed":1.78}},{"dt":1611457200,"pop":0,"visibility":10000,"dt_txt":"2021-01-24 03:00:00","weather":[{"icon":"04n","description":"overcast clouds","main":"Clouds","id":804}],"main":{"temp":272.77,"temp_min":272.77,"grnd_level":991,"temp_kf":0,"humidity":97,"pressure":997,"sea_level":997,"feels_like":269.92,"temp_max":272.77},"clouds":{"all":100},"sys":{"pod":"n"},"wind":{"deg":238,"speed":1.07}},{"dt":1611468000,"pop":0,"visibility":10000,"dt_txt":"2021-01-24 06:00:00","weather":[{"icon":"04n","description":"overcast clouds","main":"Clouds","id":804}],"main":{"temp":272.91,"temp_min":272.91,"grnd_level":992,"temp_kf":0,"humidity":97,"pressure":998,"sea_level":998,"feels_like":269.81,"temp_max":272.91},"clouds":{"all":100},"sys":{"pod":"n"},"wind":{"deg":165,"speed":1.46}},{"dt":1611478800,"pop":0,"visibility":10000,"dt_txt":"2021-01-24 09:00:00","weather":[{"icon":"04d","description":"overcast clouds","main":"Clouds","id":804}],"main":{"temp":273.65,"temp_min":273.65,"grnd_level":993,"temp_kf":0,"humidity":93,"pressure":998,"sea_level":998,"feels_like":270.19,"temp_max":273.65},"clouds":{"all":100},"sys":{"pod":"d"},"wind":{"deg":168,"speed":2.01}},{"dt":1611489600,"pop":0,"visibility":10000,"dt_txt":"2021-01-24 12:00:00","weather":[{"icon":"04d","description":"overcast clouds","main":"Clouds","id":804}],"main":{"temp":275.06,"temp_min":275.06,"grnd_level":992,"temp_kf":0,"humidity":85,"pressure":998,"sea_level":998,"feels_like":271.68,"temp_max":275.06},"clouds":{"all":100},"sys":{"pod":"d"},"wind":{"deg":184,"speed":1.92}},{"dt":1611500400,"pop":0.2,"visibility":51,"dt_txt":"2021-01-24 15:00:00","snow":{"3h":0.13},"weather":[{"icon":"13d","description":"light snow","main":"Snow","id":600}],"main":{"temp":274.48,"temp_min":274.48,"grnd_level":992,"temp_kf":0,"humidity":97,"pressure":998,"sea_level":998,"feels_like":271.53,"temp_max":274.48},"clouds":{"all":100},"sys":{"pod":"d"},"wind":{"deg":207,"speed":1.57}},{"dt":1611511200,"pop":0.38,"visibility":231,"dt_txt":"2021-01-24 18:00:00","snow":{"3h":0.34},"weather":[{"icon":"13n","description":"light snow","main":"Snow","id":600}],"main":{"temp":274.36,"temp_min":274.36,"grnd_level":993,"temp_kf":0,"humidity":96,"pressure":999,"sea_level":999,"feels_like":270.78,"temp_max":274.36},"clouds":{"all":100},"sys":{"pod":"n"},"wind":{"deg":268,"speed":2.41}},{"dt":1611522000,"pop":0.25,"visibility":10000,"dt_txt":"2021-01-24 21:00:00","weather":[{"icon":"04n","description":"overcast clouds","main":"Clouds","id":804}],"main":{"temp":273.91,"temp_min":273.91,"grnd_level":994,"temp_kf":0,"humidity":93,"pressure":999,"sea_level":999,"feels_like":269.64,"temp_max":273.91},"clouds":{"all":100},"sys":{"pod":"n"},"wind":{"deg":273,"speed":3.22}},{"dt":1611532800,"pop":0.17,"visibility":10000,"dt_txt":"2021-01-25 00:00:00","weather":[{"icon":"04n","description":"overcast clouds","main":"Clouds","id":804}],"main":{"temp":272.8,"temp_min":272.8,"grnd_level":995,"temp_kf":0,"humidity":97,"pressure":1000,"sea_level":1000,"feels_like":268.21,"temp_max":272.8},"clouds":{"all":92},"sys":{"pod":"n"},"wind":{"deg":265,"speed":3.57}},{"dt":1611543600,"pop":0,"visibility":10000,"dt_txt":"2021-01-25 03:00:00","weather":[{"icon":"01n","description":"clear sky","main":"Clear","id":800}],"main":{"temp":272.02,"temp_min":272.02,"grnd_level":996,"temp_kf":0,"humidity":97,"pressure":1001,"sea_level":1001,"feels_like":267.3,"temp_max":272.02},"clouds":{"all":1},"sys":{"pod":"n"},"wind":{"deg":268,"speed":3.6}},{"dt":1611554400,"pop":0,"visibility":10000,"dt_txt":"2021-01-25 06:00:00","weather":[{"icon":"01n","description":"clear sky","main":"Clear","id":800}],"main":{"temp":271.9,"temp_min":271.9,"grnd_level":997,"temp_kf":0,"humidity":96,"pressure":1003,"sea_level":1003,"feels_like":267.14,"temp_max":271.9},"clouds":{"all":1},"sys":{"pod":"n"},"wind":{"deg":258,"speed":3.61}},{"dt":1611565200,"pop":0,"visibility":10000,"dt_txt":"2021-01-25 09:00:00","weather":[{"icon":"01d","description":"clear sky","main":"Clear","id":800}],"main":{"temp":273.32,"temp_min":273.32,"grnd_level":999,"temp_kf":0,"humidity":93,"pressure":1004,"sea_level":1004,"feels_like":268.07,"temp_max":273.32},"clouds":{"all":0},"sys":{"pod":"d"},"wind":{"deg":257,"speed":4.5}},{"dt":1611576000,"pop":0,"visibility":10000,"dt_txt":"2021-01-25 12:00:00","weather":[{"icon":"01d","description":"clear sky","main":"Clear","id":800}],"main":{"temp":275.52,"temp_min":275.52,"grnd_level":999,"temp_kf":0,"humidity":79,"pressure":1005,"sea_level":1005,"feels_like":269.71,"temp_max":275.52},"clouds":{"all":2},"sys":{"pod":"d"},"wind":{"deg":261,"speed":5.28}},{"dt":1611586800,"pop":0,"visibility":10000,"dt_txt":"2021-01-25 15:00:00","weather":[{"icon":"01d","description":"clear sky","main":"Clear","id":800}],"main":{"temp":274.82,"temp_min":274.82,"grnd_level":1000,"temp_kf":0,"humidity":83,"pressure":1006,"sea_level":1006,"feels_like":269.78,"temp_max":274.82},"clouds":{"all":10},"sys":{"pod":"d"},"wind":{"deg":260,"speed":4.18}},{"dt":1611597600,"pop":0,"visibility":10000,"dt_txt":"2021-01-25 18:00:00","weather":[{"icon":"02n","description":"few clouds","main":"Clouds","id":801}],"main":{"temp":273.29,"temp_min":273.29,"grnd_level":1002,"temp_kf":0,"humidity":92,"pressure":1007,"sea_level":1007,"feels_like":268.22,"temp_max":273.29},"clouds":{"all":12},"sys":{"pod":"n"},"wind":{"deg":263,"speed":4.2}},{"dt":1611608400,"pop":0,"visibility":10000,"dt_txt":"2021-01-25 21:00:00","weather":[{"icon":"01n","description":"clear sky","main":"Clear","id":800}],"main":{"temp":272.61,"temp_min":272.61,"grnd_level":1003,"temp_kf":0,"humidity":93,"pressure":1009,"sea_level":1009,"feels_like":267.81,"temp_max":272.61},"clouds":{"all":6},"sys":{"pod":"n"},"wind":{"deg":262,"speed":3.71}},{"dt":1611619200,"pop":0,"visibility":10000,"dt_txt":"2021-01-26 00:00:00","weather":[{"icon":"01n","description":"clear sky","main":"Clear","id":800}],"main":{"temp":272.09,"temp_min":272.09,"grnd_level":1004,"temp_kf":0,"humidity":93,"pressure":1009,"sea_level":1009,"feels_like":267.58,"temp_max":272.09},"clouds":{"all":3},"sys":{"pod":"n"},"wind":{"deg":263,"speed":3.2}},{"dt":1611630000,"pop":0,"visibility":10000,"dt_txt":"2021-01-26 03:00:00","weather":[{"icon":"01n","description":"clear sky","main":"Clear","id":800}],"main":{"temp":271.91,"temp_min":271.91,"grnd_level":1004,"temp_kf":0,"humidity":94,"pressure":1010,"sea_level":1010,"feels_like":267.37,"temp_max":271.91},"clouds":{"all":1},"sys":{"pod":"n"},"wind":{"deg":276,"speed":3.24}},{"dt":1611640800,"pop":0,"visibility":10000,"dt_txt":"2021-01-26 06:00:00","weather":[{"icon":"02n","description":"few clouds","main":"Clouds","id":801}],"main":{"temp":271.71,"temp_min":271.71,"grnd_level":1006,"temp_kf":0,"humidity":95,"pressure":1011,"sea_level":1011,"feels_like":267.06,"temp_max":271.71},"clouds":{"all":12},"sys":{"pod":"n"},"wind":{"deg":275,"speed":3.39}},{"dt":1611651600,"pop":0,"visibility":10000,"dt_txt":"2021-01-26 09:00:00","weather":[{"icon":"03d","description":"scattered clouds","main":"Clouds","id":802}],"main":{"temp":272.76,"temp_min":272.76,"grnd_level":1007,"temp_kf":0,"humidity":94,"pressure":1012,"sea_level":1012,"feels_like":267.68,"temp_max":272.76},"clouds":{"all":31},"sys":{"pod":"d"},"wind":{"deg":272,"speed":4.17}},{"dt":1611662400,"pop":0,"visibility":10000,"dt_txt":"2021-01-26 12:00:00","weather":[{"icon":"03d","description":"scattered clouds","main":"Clouds","id":802}],"main":{"temp":274.72,"temp_min":274.72,"grnd_level":1007,"temp_kf":0,"humidity":85,"pressure":1013,"sea_level":1013,"feels_like":269.94,"temp_max":274.72},"clouds":{"all":39},"sys":{"pod":"d"},"wind":{"deg":262,"speed":3.85}}]},{"city":{"country":"FR","coord":{"lon":2.3488,"lat":48.8534},"sunrise":1611214413,"timezone":3600,"sunset":1611246598,"name":"Paris","id":2988507,"population":2138551},"cnt":40,"cod":"200","message":0,"list":[{"dt":1611241200,"pop":0.99,"rain":{"3h":0.99},"visibility":9093,"dt_txt":"2021-01-21 15:00:00","weather":[{"icon":"10d","description":"light rain","main":"Rain","id":500}],"main":{"temp":281.98,"temp_min":281.78,"grnd_level":987,"temp_kf":0.2,"humidity":79,"pressure":994,"sea_level":994,"feels_like":276.48,"temp_max":281.98},"clouds":{"all":87},"sys":{"pod":"d"},"wind":{"deg":186,"speed":6.36}},{"dt":1611252000,"pop":1,"rain":{"3h":3.02},"visibility":10000,"dt_txt":"2021-01-21 18:00:00","weather":[{"icon":"10n","description":"moderate rain","main":"Rain","id":501}],"main":{"temp":283.28,"temp_min":283.28,"grnd_level":983,"temp_kf":-0.3,"humidity":77,"pressure":990,"sea_level":990,"feels_like":276.75,"temp_max":283.58},"clouds":{"all":95},"sys":{"pod":"n"},"wind":{"deg":215,"speed":8.11}},{"dt":1611262800,"pop":0.3,"rain":{"3h":0.14},"visibility":10000,"dt_txt":"2021-01-21 21:00:00","weather":[{"icon":"10n","description":"light rain","main":"Rain","id":500}],"main":{"temp":282.44,"temp_min":282.44,"grnd_level":983,"temp_kf":-0.02,"humidity":74,"pressure":988,"sea_level":988,"feels_like":275.27,"temp_max":282.46},"clouds":{"all":98},"sys":{"pod":"n"},"wind":{"deg":215,"speed":8.6}},{"dt":1611273600,"pop":0.83,"rain":{"3h":1.32},"visibility":9094,"dt_txt":"2021-01-22 00:00:00","weather":[{"icon":"10n","description":"light rain","main":"Rain","id":500}],"main":{"temp":281.93,"temp_min":281.93,"grnd_level":984,"temp_kf":0,"humidity":79,"pressure":989,"sea_level":989,"feels_like":275.83,"temp_max":281.93},"clouds":{"all":100},"sys":{"pod":"n"},"wind":{"deg":252,"speed":7.21}},{"dt":1611284400,"pop":0.71,"rain":{"3h":1.95},"visibility":10000,"dt_txt":"2021-01-22 03:00:00","weather":[{"icon":"10n","description":"light rain","main":"Rain","id":500}],"main":{"temp":279.73,"temp_min":279.73,"grnd_level":986,"temp_kf":0,"humidity":77,"pressure":991,"sea_level":991,"feels_like":276.45,"temp_max":279.73},"clouds":{"all":100},"sys":{"pod":"n"},"wind":{"deg":312,"speed":2.5}},{"dt":1611295200,"pop":0.6,"visibility":10000,"dt_txt":"2021-01-22 06:00:00","weather":[{"icon":"04n","description":"overcast clouds","main":"Clouds","id":804}],"main":{"temp":279.06,"temp_min":279.06,"grnd_level":988,"temp_kf":0,"humidity":75,"pressure":992,"sea_level":992,"feels_like":276.59,"temp_max":279.06},"clouds":{"all":97},"sys":{"pod":"n"},"wind":{"deg":233,"speed":1.1}},{"dt":1611306000,"pop":0.21,"visibility":10000,"dt_txt":"2021-01-22 09:00:00","weather":[{"icon":"04d","description":"overcast clouds","main":"Clouds","id":804}],"main":{"temp":279.32,"temp_min":279.32,"grnd_level":989,"temp_kf":0,"humidity":72,"pressure":993,"sea_level":993,"feels_like":276.79,"temp_max":279.32},"clouds":{"all":100},"sys":{"pod":"d"},"wind":{"deg":279,"speed":1.11}},{"dt":1611316800,"pop":0.16,"visibility":10000,"dt_txt":"2021-01-22 12:00:00","weather":[{"icon":"04d","description":"overcast clouds","main":"Clouds","id":804}],"main":{"temp":280.63,"temp_min":280.63,"grnd_level":990,"temp_kf":0,"humidity":65,"pressure":995,"sea_level":995,"feels_like":277.78,"temp_max":280.63},"clouds":{"all":100},"sys":{"pod":"d"},"wind":{"deg":309,"speed":1.52}},{"dt":1611327600,"pop":0.01,"visibility":10000,"dt_txt":"2021-01-22 15:00:00","weather":[{"icon":"04d","description":"overcast clouds","main":"Clouds","id":804}],"main":{"temp":280.93,"temp_min":280.93,"grnd_level":990,"temp_kf":0,"humidity":63,"pressure":995,"sea_level":995,"feels_like":277.09,"temp_max":280.93},"clouds":{"all":100},"sys":{"pod":"d"},"wind":{"deg":299,"speed":2.9}},{"dt":1611338400,"pop":0,"visibility":10000,"dt_txt":"2021-01-22 18:00:00","weather":[{"icon":"04n","description":"overcast clouds","main":"Clouds","id":804}],"main":{"temp":279.47,"temp_min":279.47,"grnd_level":993,"temp_kf":0,"humidity":73,"pressure":997,"sea_level":997,"feels_like":276.36,"temp_max":279.47},"clouds":{"all":100},"sys":{"pod":"n"},"wind":{"deg":250,"speed":2.02}},{"dt":1611349200,"pop":0,"visibility":10000,"dt_txt":"2021-01-22 21:00:00","weather":[{"icon":"04n","description":"overcast clouds","main":"Clouds","id":804}],"main":{"temp":278.55,"temp_min":278.55,"grnd_level":993,"temp_kf":0,"humidity":79,"pressure":998,"sea_level":998,"feels_like":274.87,"temp_max":278.55},"clouds":{"all":100},"sys":{"pod":"n"},"wind":{"deg":231,"speed":2.88}},{"dt":1611360000,"pop":0,"visibility":10000,"dt_txt":"2021-01-23 00:00:00","weather":[{"icon":"04n","description":"overcast clouds","main":"Clouds","id":804}],"main":{"temp":278.01,"temp_min":278.01,"grnd_level":992,"temp_kf":0,"humidity":82,"pressure":997,"sea_level":997,"feels_like":273.64,"temp_max":278.01},"clouds":{"all":97},"sys":{"pod":"n"},"wind":{"deg":214,"speed":3.86}},{"dt":1611370800,"pop":0,"visibility":10000,"dt_txt":"2021-01-23 03:00:00","weather":[{"icon":"01n","description":"clear sky","main":"Clear","id":800}],"main":{"temp":277.11,"temp_min":277.11,"grnd_level":991,"temp_kf":0,"humidity":82,"pressure":996,"sea_level":996,"feels_like":272.44,"temp_max":277.11},"clouds":{"all":8},"sys":{"pod":"n"},"wind":{"deg":217,"speed":4.09}},{"dt":1611381600,"pop":0,"visibility":10000,"dt_txt":"2021-01-23 06:00:00","weather":[{"icon":"01n","description":"clear sky","main":"Clear","id":800}],"main":{"temp":276.2,"temp_min":276.2,"grnd_level":991,"temp_kf":0,"humidity":84,"pressure":995,"sea_level":995,"feels_like":271.86,"temp_max":276.2},"clouds":{"all":4},"sys":{"pod":"n"},"wind":{"deg":222,"speed":3.5}},{"dt":1611392400,"pop":0,"visibility":10000,"dt_txt":"2021-01-23 09:00:00","weather":[{"icon":"04d","description":"overcast clouds","main":"Clouds","id":804}],"main":{"temp":276.45,"temp_min":276.45,"grnd_level":991,"temp_kf":0,"humidity":81,"pressure":995,"sea_level":995,"feels_like":273.64,"temp_max":276.45},"clouds":{"all":90},"sys":{"pod":"d"},"wind":{"deg":209,"speed":1.26}},{"dt":1611403200,"pop":0.01,"visibility":10000,"dt_txt":"2021-01-23 12:00:00","weather":[{"icon":"04d","description":"overcast clouds","main":"Clouds","id":804}],"main":{"temp":278.39,"temp_min":278.39,"grnd_level":992,"temp_kf":0,"humidity":70,"pressure":996,"sea_level":996,"feels_like":275.77,"temp_max":278.39},"clouds":{"all":95},"sys":{"pod":"d"},"wind":{"deg":325,"speed":0.95}},{"dt":1611414000,"pop":0.44,"rain":{"3h":0.29},"visibility":10000,"dt_txt":"2021-01-23 15:00:00","weather":[{"icon":"10d","description":"light rain","main":"Rain","id":500}],"main":{"temp":278.03,"temp_min":278.03,"grnd_level":992,"temp_kf":0,"humidity":77,"pressure":997,"sea_level":997,"feels_like":273.84,"temp_max":278.03},"clouds":{"all":100},"sys":{"pod":"d"},"wind":{"deg":310,"speed":3.41}},{"dt":1611424800,"pop":0.86,"visibility":10000,"dt_txt":"2021-01-23 18:00:00","snow":{"3h":2.58},"weather":[{"icon":"13n","description":"snow","main":"Snow","id":601}],"main":{"temp":276.13,"temp_min":276.13,"grnd_level":994,"temp_kf":0,"humidity":86,"pressure":999,"sea_level":999,"feels_like":272.22,"temp_max":276.13},"clouds":{"all":100},"sys":{"pod":"n"},"wind":{"deg":315,"speed":2.94}},{"dt":1611435600,"pop":0.05,"visibility":10000,"dt_txt":"2021-01-23 21:00:00","weather":[{"icon":"03n","description":"scattered clouds","main":"Clouds","id":802}],"main":{"temp":275.78,"temp_min":275.78,"grnd_level":995,"temp_kf":0,"humidity":84,"pressure":1000,"sea_level":1000,"feels_like":272.31,"temp_max":275.78},"clouds":{"all":46},"sys":{"pod":"n"},"wind":{"deg":264,"speed":2.16}},{"dt":1611446400,"pop":0.02,"visibility":10000,"dt_txt":"2021-01-24 00:00:00","weather":[{"icon":"02n","description":"few clouds","main":"Clouds","id":801}],"main":{"temp":274.97,"temp_min":274.97,"grnd_level":996,"temp_kf":0,"humidity":86,"pressure":1001,"sea_level":1001,"feels_like":271.38,"temp_max":274.97},"clouds":{"all":23},"sys":{"pod":"n"},"wind":{"deg":250,"speed":2.24}},{"dt":1611457200,"pop":0,"visibility":10000,"dt_txt":"2021-01-24 03:00:00","weather":[{"icon":"01n","description":"clear sky","main":"Clear","id":800}],"main":{"temp":274.43,"temp_min":274.43,"grnd_level":996,"temp_kf":0,"humidity":88,"pressure":1001,"sea_level":1001,"feels_like":270.84,"temp_max":274.43},"clouds":{"all":8},"sys":{"pod":"n"},"wind":{"deg":231,"speed":2.19}},{"dt":1611468000,"pop":0,"visibility":10000,"dt_txt":"2021-01-24 06:00:00","weather":[{"icon":"03n","description":"scattered clouds","main":"Clouds","id":802}],"main":{"temp":274.59,"temp_min":274.59,"grnd_level":996,"temp_kf":0,"humidity":87,"pressure":1001,"sea_level":1001,"feels_like":270.84,"temp_max":274.59},"clouds":{"all":45},"sys":{"pod":"n"},"wind":{"deg":192,"speed":2.42}},{"dt":1611478800,"pop":0.72,"visibility":127,"dt_txt":"2021-01-24 09:00:00","snow":{"3h":1.91},"weather":[{"icon":"13d","description":"snow","main":"Snow","id":601}],"main":{"temp":274.05,"temp_min":274.05,"grnd_level":994,"temp_kf":0,"humidity":94,"pressure":999,"sea_level":999,"feels_like":268.98,"temp_max":274.05},"clouds":{"all":100},"sys":{"pod":"d"},"wind":{"deg":185,"speed":4.42}},{"dt":1611489600,"pop":1,"visibility":10000,"dt_txt":"2021-01-24 12:00:00","snow":{"3h":1.19},"weather":[{"icon":"13d","description":"light snow","main":"Snow","id":600}],"main":{"temp":276.8,"temp_min":276.8,"grnd_level":993,"temp_kf":0,"humidity":80,"pressure":998,"sea_level":998,"feels_like":272.05,"temp_max":276.8},"clouds":{"all":100},"sys":{"pod":"d"},"wind":{"deg":223,"speed":4.06}},{"dt":1611500400,"pop":0.54,"visibility":10000,"dt_txt":"2021-01-24 15:00:00","snow":{"3h":0.19},"weather":[{"icon":"13d","description":"light snow","main":"Snow","id":600}],"main":{"temp":277.5,"temp_min":277.5,"grnd_level":993,"temp_kf":0,"humidity":72,"pressure":998,"sea_level":998,"feels_like":271.79,"temp_max":277.5},"clouds":{"all":90},"sys":{"pod":"d"},"wind":{"deg":251,"speed":5.27}},{"dt":1611511200,"pop":0.35,"visibility":10000,"dt_txt":"2021-01-24 18:00:00","snow":{"3h":0.17},"weather":[{"icon":"13n","description":"light snow","main":"Snow","id":600}],"main":{"temp":275.74,"temp_min":275.74,"grnd_level":995,"temp_kf":0,"humidity":82,"pressure":1000,"sea_level":1000,"feels_like":269.26,"temp_max":275.74},"clouds":{"all":90},"sys":{"pod":"n"},"wind":{"deg":289,"speed":6.38}},{"dt":1611522000,"pop":0.17,"visibility":10000,"dt_txt":"2021-01-24 21:00:00","weather":[{"icon":"04n","description":"broken clouds","main":"Clouds","id":803}],"main":{"temp":274.81,"temp_min":274.81,"grnd_level":998,"temp_kf":0,"humidity":86,"pressure":1003,"sea_level":1003,"feels_like":268.87,"temp_max":274.81},"clouds":{"all":52},"sys":{"pod":"n"},"wind":{"deg":316,"speed":5.56}},{"dt":1611532800,"pop":0.03,"visibility":10000,"dt_txt":"2021-01-25 00:00:00","weather":[{"icon":"03n","description":"scattered clouds","main":"Clouds","id":802}],"main":{"temp":273.89,"temp_min":273.89,"grnd_level":1002,"temp_kf":0,"humidity":91,"pressure":1007,"sea_level":1007,"feels_like":269.74,"temp_max":273.89},"clouds":{"all":39},"sys":{"pod":"n"},"wind":{"deg":297,"speed":2.98}},{"dt":1611543600,"pop":0,"visibility":10000,"dt_txt":"2021-01-25 03:00:00","weather":[{"icon":"04n","description":"broken clouds","main":"Clouds","id":803}],"main":{"temp":273.9,"temp_min":273.9,"grnd_level":1004,"temp_kf":0,"humidity":93,"pressure":1009,"sea_level":1009,"feels_like":270.09,"temp_max":273.9},"clouds":{"all":63},"sys":{"pod":"n"},"wind":{"deg":250,"speed":2.55}},{"dt":1611554400,"pop":0.2,"visibility":9489,"dt_txt":"2021-01-25 06:00:00","snow":{"3h":0.24},"weather":[{"icon":"13n","description":"light snow","main":"Snow","id":600}],"main":{"temp":274.47,"temp_min":274.47,"grnd_level":1005,"temp_kf":0,"humidity":89,"pressure":1010,"sea_level":1010,"feels_like":269.58,"temp_max":274.47},"clouds":{"all":80},"sys":{"pod":"n"},"wind":{"deg":238,"speed":4.09}},{"dt":1611565200,"pop":0.43,"visibility":10000,"dt_txt":"2021-01-25 09:00:00","snow":{"3h":0.27},"weather":[{"icon":"13d","description":"light snow","main":"Snow","id":600}],"main":{"temp":275.92,"temp_min":275.92,"grnd_level":1006,"temp_kf":0,"humidity":79,"pressure":1011,"sea_level":1011,"feels_like":270.25,"temp_max":275.92},"clouds":{"all":99},"sys":{"pod":"d"},"wind":{"deg":257,"speed":5.16}},{"dt":1611576000,"pop":0.38,"visibility":10000,"dt_txt":"2021-01-25 12:00:00","weather":[{"icon":"04d","description":"overcast clouds","main":"Clouds","id":804}],"main":{"temp":278.94,"temp_min":278.94,"grnd_level":1007,"temp_kf":0,"humidity":65,"pressure":1012,"sea_level":1012,"feels_like":272.52,"temp_max":278.94},"clouds":{"all":88},"sys":{"pod":"d"},"wind":{"deg":273,"speed":6.28}},{"dt":1611586800,"pop":0.34,"rain":{"3h":0.17},"visibility":10000,"dt_txt":"2021-01-25 15:00:00","weather":[{"icon":"10d","description":"light rain","main":"Rain","id":500}],"main":{"temp":279.09,"temp_min":279.09,"grnd_level":1008,"temp_kf":0,"humidity":66,"pressure":1012,"sea_level":1012,"feels_like":273.38,"temp_max":279.09},"clouds":{"all":93},"sys":{"pod":"d"},"wind":{"deg":267,"speed":5.34}},{"dt":1611597600,"pop":0.01,"visibility":10000,"dt_txt":"2021-01-25 18:00:00","weather":[{"icon":"04n","description":"overcast clouds","main":"Clouds","id":804}],"main":{"temp":277.16,"temp_min":277.16,"grnd_level":1010,"temp_kf":0,"humidity":77,"pressure":1015,"sea_level":1015,"feels_like":272.38,"temp_max":277.16},"clouds":{"all":94},"sys":{"pod":"n"},"wind":{"deg":259,"speed":4.07}},{"dt":1611608400,"pop":0,"visibility":10000,"dt_txt":"2021-01-25 21:00:00","weather":[{"icon":"02n","description":"few clouds","main":"Clouds","id":801}],"main":{"temp":276.07,"temp_min":276.07,"grnd_level":1011,"temp_kf":0,"humidity":81,"pressure":1016,"sea_level":1016,"feels_like":271.97,"temp_max":276.07},"clouds":{"all":17},"sys":{"pod":"n"},"wind":{"deg":254,"speed":3.02}},{"dt":1611619200,"pop":0,"visibility":10000,"dt_txt":"2021-01-26 00:00:00","weather":[{"icon":"02n","description":"few clouds","main":"Clouds","id":801}],"main":{"temp":275.43,"temp_min":275.43,"grnd_level":1012,"temp_kf":0,"humidity":83,"pressure":1017,"sea_level":1017,"feels_like":271.52,"temp_max":275.43},"clouds":{"all":20},"sys":{"pod":"n"},"wind":{"deg":252,"speed":2.68}},{"dt":1611630000,"pop":0,"visibility":10000,"dt_txt":"2021-01-26 03:00:00","weather":[{"icon":"03n","description":"scattered clouds","main":"Clouds","id":802}],"main":{"temp":274.92,"temp_min":274.92,"grnd_level":1013,"temp_kf":0,"humidity":86,"pressure":1018,"sea_level":1018,"feels_like":271.24,"temp_max":274.92},"clouds":{"all":39},"sys":{"pod":"n"},"wind":{"deg":244,"speed":2.35}},{"dt":1611640800,"pop":0,"visibility":10000,"dt_txt":"2021-01-26 06:00:00","weather":[{"icon":"04n","description":"broken clouds","main":"Clouds","id":803}],"main":{"temp":274.67,"temp_min":274.67,"grnd_level":1013,"temp_kf":0,"humidity":90,"pressure":1018,"sea_level":1018,"feels_like":271.37,"temp_max":274.67},"clouds":{"all":65},"sys":{"pod":"n"},"wind":{"deg":242,"speed":1.89}},{"dt":1611651600,"pop":0,"visibility":10000,"dt_txt":"2021-01-26 09:00:00","weather":[{"icon":"04d","description":"overcast clouds","main":"Clouds","id":804}],"main":{"temp":275.74,"temp_min":275.74,"grnd_level":1014,"temp_kf":0,"humidity":88,"pressure":1019,"sea_level":1019,"feels_like":272.39,"temp_max":275.74},"clouds":{"all":98},"sys":{"pod":"d"},"wind":{"deg":207,"speed":2.12}},{"dt":1611662400,"pop":0,"visibility":10000,"dt_txt":"2021-01-26 12:00:00","weather":[{"icon":"04d","description":"overcast clouds","main":"Clouds","id":804}],"main":{"temp":278.08,"temp_min":278.08,"grnd_level":1013,"temp_kf":0,"humidity":81,"pressure":1018,"sea_level":1018,"feels_like":273.61,"temp_max":278.08},"clouds":{"all":99},"sys":{"pod":"d"},"wind":{"deg":202,"speed":3.98}}]}]
